pysheet.py
pysheet-0.3.14.dist-info/DESCRIPTION.rst
pysheet-0.3.14.dist-info/top_level.txt
pysheet-0.3.14.dist-info/WHEEL
pysheet-0.3.14.dist-info/RECORD
pysheet-0.3.14.dist-info/METADATA
pysheet-0.3.14.dist-info/entry_points.txt
pysheet-0.3.14.dist-info/pydist.json
pysheet-0.3.14.data/scripts/pysheet
pysheet/pysheet.py
pysheet/__init__.py
