Metadata-Version: 2.0
Name: pysheet
Version: 0.3.14
Summary: Read, write and manipulate delimited text files
Home-page: https://github.com/isthisthat/Pysheet
Author: Stathis Kanterakis
Author-email: me@stathiskanterakis.com
License: LGPL
Download-URL: https://github.com/isthisthat/Pysheet/archive/0.3.14.tar.gz
Platform: UNKNOWN
Classifier: Development Status :: 5 - Production/Stable
Classifier: Intended Audience :: Developers
Classifier: Natural Language :: English
Classifier: License :: OSI Approved :: GNU Library or Lesser General Public License (LGPL)
Classifier: Operating System :: OS Independent
Classifier: Programming Language :: Python
Classifier: Programming Language :: Python :: 2
Classifier: Programming Language :: Python :: 2.6
Classifier: Programming Language :: Python :: 2.7
Classifier: Topic :: Software Development :: Libraries :: Python Modules
Requires-Dist: natsort
